getip.py
getip2-1.6.dist-info/DESCRIPTION.rst
getip2-1.6.dist-info/METADATA
getip2-1.6.dist-info/RECORD
getip2-1.6.dist-info/WHEEL
getip2-1.6.dist-info/metadata.json
getip2-1.6.dist-info/top_level.txt
