Metadata-Version: 2.0
Name: getip2
Version: 1.6
Summary: Gets your public IP Address
Home-page: https://github.com/4A47/getip2
Author: JG
Author-email: lundy11111@gmail.com
License: UNKNOWN
Platform: UNKNOWN
